odoo10_addon_sale_partner_version-10.0.1.0.1-py3.8-nspkg.pth
odoo/addons/sale_partner_version/README.rst
odoo/addons/sale_partner_version/__init__.py
odoo/addons/sale_partner_version/__manifest__.py
odoo/addons/sale_partner_version/i18n/ca.po
odoo/addons/sale_partner_version/i18n/es.po
odoo/addons/sale_partner_version/i18n/sale_partner_version.pot
odoo/addons/sale_partner_version/models/__init__.py
odoo/addons/sale_partner_version/models/res_partner.py
odoo/addons/sale_partner_version/static/description/icon.png
odoo/addons/sale_partner_version/tests/__init__.py
odoo/addons/sale_partner_version/tests/test_sale_partner_version.py
odoo10_addon_sale_partner_version-10.0.1.0.1.dist-info/METADATA
odoo10_addon_sale_partner_version-10.0.1.0.1.dist-info/WHEEL
odoo10_addon_sale_partner_version-10.0.1.0.1.dist-info/namespace_packages.txt
odoo10_addon_sale_partner_version-10.0.1.0.1.dist-info/top_level.txt
odoo10_addon_sale_partner_version-10.0.1.0.1.dist-info/RECORD
